emoji_extractor/__init__.py
emoji_extractor/extract.py
emoji_extractor/data/big_regex.pkl
emoji_extractor/data/possible_emoji.pkl
emoji_extractor/data/tme_regex.pkl
emoji_extractor-16.0.data/data/emoji_extractor/big_regex.pkl
emoji_extractor-16.0.data/data/emoji_extractor/possible_emoji.pkl
emoji_extractor-16.0.data/data/emoji_extractor/tme_regex.pkl
emoji_extractor-16.0.dist-info/LICENSE.txt
emoji_extractor-16.0.dist-info/METADATA
emoji_extractor-16.0.dist-info/WHEEL
emoji_extractor-16.0.dist-info/top_level.txt
emoji_extractor-16.0.dist-info/RECORD
